{"metric": {"freeOperatingCashFlow/revenue5Y": 26.97743, "freeOperatingCashFlow/revenueTTM": 19.86139, "grossMargin5Y": 85.04189, "grossMarginAnnual": 84.59709, "grossMarginTTM": 83.29575, "netProfitMargin5Y": 17.97374, "netProfitMarginAnnual": 15.58519, "netProfitMarginTTM": 13.11341, "operatingMargin5Y": 19.96997, "operatingMarginAnnual": 18.80953, "operatingMarginTTM": 15.85247, "pretaxMargin5Y": 18.75229, "pretaxMarginAnnual": 17.14339, "pretaxMarginTTM": 14.13384}, "metricType": "margin", "symbol": "CTXS"}