{"metric": {"freeOperatingCashFlow/revenue5Y": -6.04432, "freeOperatingCashFlow/revenueTTM": -2.66745, "grossMargin5Y": 23.56658, "grossMarginAnnual": 22.08267, "grossMarginTTM": 22.89576, "netProfitMargin5Y": -2.11927, "netProfitMarginAnnual": 7.18421, "netProfitMarginTTM": -0.782, "operatingMargin5Y": -0.51061, "operatingMarginAnnual": 12.31992, "operatingMarginTTM": -3.77747, "pretaxMargin5Y": -3.86349, "pretaxMarginAnnual": 6.52734, "pretaxMarginTTM": -1.36456}, "metricType": "margin", "symbol": "GE"}